aws_helper/__init__.py
github_helper/__init__.py
hyperion/__init__.py
supercell_tools-0.0.5.dist-info/DESCRIPTION.rst
supercell_tools-0.0.5.dist-info/METADATA
supercell_tools-0.0.5.dist-info/RECORD
supercell_tools-0.0.5.dist-info/WHEEL
supercell_tools-0.0.5.dist-info/metadata.json
supercell_tools-0.0.5.dist-info/top_level.txt
supportbot/__init__.py
