Metadata-Version: 2.0
Name: supercell-tools
Version: 0.0.5
Summary: UNKNOWN
Home-page: UNKNOWN
Author: Super Cell
Author-email: SprintTeamSuperCell@capitalone.com
License: Creative Commons Attribution-Noncommercial-Share Alike license
Platform: UNKNOWN
